[{"pair":[["btc","usd"],[0,60942.03]]},{"pair":[["eth","usd"],[0,2886.93]]},{"pair":[["ltc","usd"],[0,79.83]]},{"pair":[["usdt","usd"],[0,1.0002]]},{"pair":[["aud","usd"],[0,0.65961]]},{"pair":[["cad","usd"],[0,0.7309781218248137]]},{"pair":[["eur","usd"],[0,1.07722]]},{"pair":[["jpy","usd"],[0,0.006417661404184315]]},{"pair":[["kes","usd"],[0,0.007341065922771986]]},{"pair":[["nok","usd"],[0,0.09207738551788466]]},{"pair":[["nzd","usd"],[0,0.60095]]},{"pair":[["zar","usd"],[0,0.05434144687362788]]},{"pair":[["sek","usd"],[0,0.09222888627163806]]},{"pair":[["gbp","usd"],[0,1.25246]]},{"pair":[["chf","usd"],[0,0.90658]]}]